arglu/__init__.py
arglu/file_type_utils.py
arglu/graph_processing.py
arglu/mutable_tree.py
arglu/node.py
arglu/plot_argument_graphs.py
arglu-2.1.4.dist-info/METADATA
arglu-2.1.4.dist-info/WHEEL
arglu-2.1.4.dist-info/licenses/LICENSE
arglu-2.1.4.dist-info/RECORD
