Metadata-Version: 2.1
Name: arglu
Version: 2.1.4
Summary: Some utilities for Argument Mining
Project-URL: Homepage, https://github.com/pypa/sampleproject
Project-URL: Bug Tracker, https://github.com/pypa/sampleproject/issues
Author-email: Jonathan Clayton <jaclayton2@sheffield.ac.uk>
License-File: LICENSE
Classifier: License :: OSI Approved :: MIT License
Classifier: Operating System :: OS Independent
Classifier: Programming Language :: Python :: 3
Requires-Python: >=3.7
Requires-Dist: matplotlib
Requires-Dist: networkx
Requires-Dist: numpy
